odoo/addons/account_move_line_used_currency/README.rst
odoo/addons/account_move_line_used_currency/__init__.py
odoo/addons/account_move_line_used_currency/__manifest__.py
odoo/addons/account_move_line_used_currency/init_hooks.py
odoo/addons/account_move_line_used_currency/i18n/account_move_line_used_currency.pot
odoo/addons/account_move_line_used_currency/i18n/es.po
odoo/addons/account_move_line_used_currency/i18n/it.po
odoo/addons/account_move_line_used_currency/models/__init__.py
odoo/addons/account_move_line_used_currency/models/account_move_line.py
odoo/addons/account_move_line_used_currency/readme/CONTRIBUTORS.rst
odoo/addons/account_move_line_used_currency/readme/DESCRIPTION.rst
odoo/addons/account_move_line_used_currency/static/description/icon.png
odoo/addons/account_move_line_used_currency/static/description/index.html
odoo/addons/account_move_line_used_currency/tests/__init__.py
odoo/addons/account_move_line_used_currency/tests/test_account_move_line_used_currency.py
odoo/addons/account_move_line_used_currency/views/account_move_line_view.xml
odoo/addons/account_move_line_used_currency/views/account_move_view.xml
odoo14_addon_account_move_line_used_currency-14.0.1.0.1.dev8.dist-info/METADATA
odoo14_addon_account_move_line_used_currency-14.0.1.0.1.dev8.dist-info/WHEEL
odoo14_addon_account_move_line_used_currency-14.0.1.0.1.dev8.dist-info/top_level.txt
odoo14_addon_account_move_line_used_currency-14.0.1.0.1.dev8.dist-info/RECORD
