Metadata-Version: 2.1
Name: odoo14-addon-account_move_line_used_currency
Version: 14.0.1.0.1.dev8
Summary: Account Move Line Amount Currency
Home-page: https://github.com/OCA/account-financial-tools
Author: ForgeFlow, Odoo Community Association (OCA)
Author-email: support@odoo-community.org
License: LGPL-3
Classifier: Programming Language :: Python
Classifier: Framework :: Odoo
Classifier: Framework :: Odoo :: 14.0
Classifier: License :: OSI Approved :: GNU Lesser General Public License v3 (LGPLv3)
Requires-Python: >=3.6
Requires-Dist: odoo<14.1dev,>=14.0a
